{"stat.pickup.minecraft.wooden_slab":30,"stat.pickup.minecraft.redstone_torch":2,"stat.horseOneCm":338766,"stat.useItem.minecraft.iron_axe":140,"stat.leaveGame":4,"stat.mineBlock.minecraft.cobblestone":100,"stat.mineBlock.minecraft.pumpkin":3,"stat.pickup.minecraft.flint":20,"stat.mineBlock.minecraft.yellow_flower":4,"stat.craftItem.minecraft.iron_axe":1,"stat.mineBlock.minecraft.brown_mushroom":9,"stat.pickup.minecraft.flower_pot":4,"stat.swimOneCm":35014,"stat.climbOneCm":80011,"stat.useItem.minecraft.planks":66,"stat.craftItem.minecraft.stone_pressure_plate":1,"stat.breakItem.minecraft.iron_pickaxe":4,"stat.useItem.minecraft.redstone_torch":19,"stat.useItem.minecraft.dirt":292,"stat.useItem.minecraft.water_bucket":39,"stat.mineBlock.minecraft.red_mushroom":3,"stat.pickup.minecraft.stone_hoe":1,"stat.pickup.minecraft.sand":49,"stat.craftItem.minecraft.furnace":2,"stat.useItem.minecraft.red_flower":39,"stat.useItem.minecraft.egg":4,"stat.craftItem.minecraft.stone_axe":1,"stat.craftItem.minecraft.trapdoor":4,"stat.craftItem.minecraft.melon_block":14,"stat.pickup.minecraft.cobblestone_wall":4,"stat.craftItem.minecraft.stone_pickaxe":8,"stat.useItem.minecraft.rail":58,"stat.pickup.minecraft.shears":1,"stat.pickup.minecraft.cobblestone":1411,"stat.mineBlock.minecraft.wooden_slab":30,"stat.craftItem.minecraft.cobblestone_wall":54,"stat.useItem.minecraft.stone_shovel":133,"stat.flyOneCm":609,"stat.craftItem.minecraft.glass_bottle":3,"stat.pickup.minecraft.brown_mushroom":20,"stat.mineBlock.minecraft.sand":49,"stat.craftItem.minecraft.wooden_slab":378,"stat.pickup.minecraft.cactus":7,"stat.pickup.minecraft.redstone":329,"stat.mineBlock.minecraft.iron_ore":167,"stat.timeSinceDeath":549703,"stat.craftItem.minecraft.blaze_powder":8,"stat.hopperInspected":6,"stat.useItem.minecraft.iron_pickaxe":1007,"stat.cauldronFilled":1,"stat.craftItem.minecraft.wooden_pickaxe":1,"stat.useItem.minecraft.wooden_slab":254,"stat.pickup.minecraft.double_plant":30,"stat.killEntity.Bat":1,"stat.craftItem.minecraft.bed":1,"stat.craftItem.minecraft.glass_pane":96,"stat.mineBlock.minecraft.hopper":1,"stat.pickup.minecraft.melon_block":14,"stat.useItem.minecraft.oak_stairs":82,"stat.furnaceInteraction":32,"stat.pickup.minecraft.redstone_lamp":2,"stat.mineBlock.minecraft.rail":1,"stat.pickup.minecraft.trapdoor":2,"stat.mineBlock.minecraft.coal_ore":301,"stat.craftItem.minecraft.stone_hoe":1,"stat.mineBlock.minecraft.ladder":12,"stat.useItem.minecraft.double_plant":6,"stat.useItem.minecraft.minecart":1,"stat.pickup.minecraft.furnace":1,"stat.mineBlock.minecraft.redstone_lamp":2,"stat.pickup.minecraft.cauldron":1,"stat.useItem.minecraft.trapdoor":6,"stat.sprintOneCm":6304,"stat.useItem.minecraft.diamond_shovel":532,"stat.mineBlock.minecraft.stone_slab":9,"stat.useItem.minecraft.fence":115,"stat.useItem.minecraft.stone_stairs":108,"stat.craftItem.minecraft.wooden_axe":1,"stat.craftItem.minecraft.stick":220,"stat.useItem.minecraft.stone_slab":240,"stat.useItem.minecraft.bed":2,"stat.pickup.minecraft.stone_stairs":17,"stat.craftItem.minecraft.stone":4,"stat.useItem.minecraft.cauldron":1,"stat.mineBlock.minecraft.diamond_ore":22,"stat.mineBlock.minecraft.fence":15,"stat.useItem.minecraft.wheat_seeds":121,"stat.mineBlock.minecraft.crafting_table":4,"stat.useItem.minecraft.wooden_button":1,"stat.useItem.minecraft.stone_pressure_plate":1,"stat.useItem.minecraft.diamond_pickaxe":286,"stat.useItem.minecraft.hopper":5,"stat.craftItem.minecraft.redstone_lamp":8,"stat.useItem.minecraft.bucket":41,"stat.mineBlock.minecraft.oak_stairs":2,"stat.mineBlock.minecraft.planks":58,"stat.drop":1,"stat.pickup.minecraft.egg":10,"stat.playOneMinute":549703,"stat.useItem.minecraft.ladder":27,"stat.craftItem.minecraft.iron_pickaxe":4,"stat.craftItem.minecraft.diamond_pickaxe":1,"stat.mineBlock.minecraft.gold_ore":12,"stat.mineBlock.minecraft.tallgrass":966,"stat.diveOneCm":1866,"stat.craftItem.minecraft.slime_ball":1,"stat.pickup.minecraft.wheat":63,"stat.chestOpened":308,"stat.pickup.minecraft.pumpkin":6,"stat.craftItem.minecraft.ladder":15,"stat.useItem.minecraft.stone":60,"stat.pickup.minecraft.gravel":175,"stat.craftItem.minecraft.redstone_torch":18,"stat.breakItem.minecraft.wooden_axe":1,"stat.craftItem.minecraft.golden_rail":18,"stat.craftItem.minecraft.coal":3,"stat.useItem.minecraft.flower_pot":4,"stat.jump":2214,"stat.useItem.minecraft.sand":1,"stat.pickup.minecraft.fence":15,"stat.pickup.minecraft.coal":416,"stat.fallOneCm":10657,"stat.pickup.minecraft.carrot":44,"stat.useItem.minecraft.stone_axe":132,"stat.craftItem.minecraft.bread":7,"stat.crouchOneCm":21499,"stat.mineBlock.minecraft.chest":7,"stat.pickup.minecraft.rail":1,"stat.craftItem.minecraft.chest":22,"stat.craftItem.minecraft.torch":44,"stat.craftItem.minecraft.iron_ingot":120,"stat.pickup.minecraft.dirt":1024,"stat.pickup.minecraft.red_mushroom":6,"stat.pickup.minecraft.melon":60,"stat.craftItem.minecraft.rail":144,"stat.craftItem.minecraft.hopper":4,"stat.craftingTableInteraction":95,"stat.pickup.minecraft.iron_ore":164,"stat.pickup.minecraft.gold_ore":12,"stat.useItem.minecraft.sapling":68,"stat.mineBlock.minecraft.lapis_ore":4,"stat.useItem.minecraft.redstone_lamp":10,"stat.mineBlock.minecraft.stone_stairs":17,"stat.brewingstandInteraction":1,"stat.useItem.minecraft.golden_rail":18,"stat.damageTaken":20,"stat.craftItem.minecraft.wooden_button":1,"stat.mineBlock.minecraft.red_flower":28,"stat.mineBlock.minecraft.torch":62,"stat.mineBlock.minecraft.melon_block":11,"stat.mineBlock.minecraft.furnace":1,"stat.useItem.minecraft.wooden_pickaxe":60,"stat.useItem.minecraft.furnace":3,"stat.mineBlock.minecraft.sapling":4,"stat.pickup.minecraft.dye":28,"stat.pickup.minecraft.planks":58,"stat.pickup.minecraft.reeds":41,"stat.pickup.minecraft.bed":1,"stat.cauldronUsed":5,"stat.pickup.minecraft.wheat_seeds":284,"stat.pickup.minecraft.potato":62,"stat.pickup.minecraft.oak_stairs":2,"stat.pickup.minecraft.lead":21,"stat.mineBlock.minecraft.gravel":195,"stat.useItem.minecraft.stone_pickaxe":1057,"stat.breakItem.minecraft.stone_axe":1,"stat.damageDealt":60,"stat.sleepInBed":8,"stat.craftItem.minecraft.oak_stairs":80,"stat.useItem.minecraft.crafting_table":5,"stat.mineBlock.minecraft.dirt":848,"stat.craftItem.minecraft.stone_slab":372,"stat.flowerPotted":4,"stat.craftItem.minecraft.stone_shovel":1,"stat.walkOneCm":3531271,"stat.useItem.minecraft.torch":170,"stat.useItem.minecraft.bread":3,"stat.animalsBred":5,"stat.useItem.minecraft.chest":25,"stat.drop.minecraft.wheat":1,"stat.pickup.minecraft.stick":2,"stat.craftItem.minecraft.redstone_block":8,"stat.craftItem.minecraft.stone_stairs":92,"stat.pickup.minecraft.crafting_table":4,"stat.useItem.minecraft.cobblestone":1232,"stat.craftItem.minecraft.crafting_table":1,"stat.useItem.minecraft.gravel":22,"stat.mineBlock.minecraft.double_plant":35,"stat.breakItem.minecraft.stone_pickaxe":8,"stat.minecartOneCm":28125,"stat.pickup.minecraft.log":202,"stat.useItem.minecraft.redstone_block":8,"stat.pickup.minecraft.stone":345,"stat.pickup.minecraft.hopper":1,"stat.pickup.minecraft.sapling":249,"stat.pickup.minecraft.wooden_door":4,"stat.craftItem.minecraft.brewing_stand":1,"stat.craftItem.minecraft.minecart":1,"stat.pickup.minecraft.apple":12,"stat.pickup.minecraft.ladder":15,"stat.useItem.minecraft.glass_pane":92,"stat.breakItem.minecraft.stone_shovel":1,"stat.pickup.minecraft.gold_ingot":3,"stat.pickup.minecraft.beetroot":18,"stat.mineBlock.minecraft.cactus":2,"stat.craftItem.minecraft.bucket":2,"stat.craftItem.minecraft.planks":731,"stat.mineBlock.minecraft.redstone_torch":2,"stat.mobKills":1,"stat.mineBlock.minecraft.log":202,"stat.craftItem.minecraft.wooden_door":6,"stat.craftItem.minecraft.shears":1,"stat.craftItem.minecraft.fence":102,"stat.useItem.minecraft.stone_hoe":130,"stat.useItem.minecraft.wooden_door":7,"stat.craftItem.minecraft.lead":2,"stat.craftItem.minecraft.sugar":8,"stat.useItem.minecraft.cobblestone_wall":55,"stat.pickup.minecraft.diamond":22,"stat.mineBlock.minecraft.leaves":424,"stat.pickup.minecraft.beetroot_seeds":37,"stat.pickup.minecraft.torch":76,"stat.pickup.minecraft.red_flower":67,"stat.useItem.minecraft.beetroot_seeds":23,"stat.mineBlock.minecraft.redstone_ore":74,"stat.sneakTime":7527,"stat.pickup.minecraft.wool":27,"stat.mineBlock.minecraft.cobblestone_wall":4,"stat.useItem.minecraft.wooden_axe":65,"stat.pickup.minecraft.stone_slab":10,"stat.useItem.minecraft.brewing_stand":1,"stat.pickup.minecraft.yellow_flower":10,"stat.mineBlock.minecraft.stone":1691,"stat.pickup.minecraft.chest":7,"stat.breakItem.minecraft.wooden_pickaxe":1}